[
	{ "s": "FACILITA", "p": [16, 14, 2] },
	{ "s": "FACILITANDO", "p": [12, 9] },
	{ "s": "FACILITAR", "p": [11, 7, 3] },
	{ "s": "FACTURACIÓN", "p": [3] },
	{ "s": "FALTANTES", "p": [8] },
	{ "s": "FECHA", "p": [8, 5] },
	{ "s": "FECHAS", "p": [8] },
	{ "s": "FILA", "p": [12] },
	{ "s": "FILTRAR", "p": [16, 14, 5] },
	{ "s": "FILTROS", "p": [8, 5] },
	{ "s": "FINALIZADOS", "p": [15] },
	{ "s": "FINALIZAR", "p": [4] },
	{ "s": "FLUJO", "p": [15] },
	{ "s": "FORMA", "p": [3] },
	{ "s": "FORMATO", "p": [9, 5] },
	{ "s": "FORMATOS", "p": [8, 5] },
	{ "s": "FORMULARIO", "p": [13, 9, 11, 10, 7, 12, 8, 5, 6, 4] },
	{ "s": "FRECUENTEMENTE", "p": [15] },
	{ "s": "FRESCA", "p": [11] },
	{ "s": "FUNCIONAL", "p": [16, 14] },
	{ "s": "FUNCIONALIDADES", "p": [8, 5] },
	{ "s": "FUNCIONES", "p": [5, 3, 6] },
	{ "s": "FUNCIÓN", "p": [5, 8, 7] },
	{ "s": "FUTURAS", "p": [4] },
	{ "s": "FÁCIL", "p": [3] },
	{ "s": "FÁCILES", "p": [12, 11] },
	{ "s": "FÍSICA", "p": [9] },
	{ "s": "FÍSICO", "p": [6] }
]