[
	{ "s": "RANGO", "p": [8, 5] },
	{ "s": "REABASTECIMIENTO", "p": [8] },
	{ "s": "REAL", "p": [13, 6] },
	{ "s": "REALIZA", "p": [13, 5, 8, 6] },
	{ "s": "REALIZADOS", "p": [13] },
	{ "s": "REALIZAR", "p": [12, 13, 8, 7, 3, 2] },
	{ "s": "RECARGA", "p": [11, 16, 14, 13, 10, 9, 8, 7] },
	{ "s": "RECARGAR", "p": [16, 14] },
	{ "s": "RECIBOS", "p": [5] },
	{ "s": "RECIÉN", "p": [6] },
	{ "s": "RECOMENDACIONES", "p": [16, 15, 14, 13, 12, 11, 10, 9, 8, 7, 6, 5, 4] },
	{ "s": "RECORDAR", "p": [4] },
	{ "s": "RECUERDE", "p": [4] },
	{ "s": "REDIRIGE", "p": [12, 8, 5] },
	{ "s": "REDIRIGIDO", "p": [4] },
	{ "s": "REFLEJARÁN", "p": [6] },
	{ "s": "REFRESCAR", "p": [15] },
	{ "s": "REFRESCOS", "p": [16, 14] },
	{ "s": "REGISTRA", "p": [10, 9, 11, 7] },
	{ "s": "REGISTRADA", "p": [4] },
	{ "s": "REGISTRADAS", "p": [6, 15] },
	{ "s": "REGISTRADO", "p": [11, 8, 4] },
	{ "s": "REGISTRADOS", "p": [12, 9, 8] },
	{ "s": "REGISTRAR", "p": [4, 11, 10, 9, 8, 7, 16, 14, 12, 6] },
	{ "s": "REGISTRARSE", "p": [4] },
	{ "s": "REGISTRARÁ", "p": [16, 14] },
	{ "s": "REGISTRO", "p": [12, 8, 4, 15, 6] },
	{ "s": "REGISTROS", "p": [8] },
	{ "s": "REGISTRÓ", "p": [15] },
	{ "s": "REGRESAR", "p": [12] },
	{ "s": "REGULARMENTE", "p": [8] },
	{ "s": "REINICIA", "p": [16, 14] },
	{ "s": "REINICIAR", "p": [16, 14] },
	{ "s": "RELEVANTES", "p": [2] },
	{ "s": "REORDEN", "p": [8] },
	{ "s": "REPITA", "p": [7] },
	{ "s": "REPITE", "p": [16, 15, 14] },
	{ "s": "REPRESENTAN", "p": [15] },
	{ "s": "REPRESENTANTE", "p": [9] },
	{ "s": "REPRESENTATIVO", "p": [10, 7] },
	{ "s": "REPRESENTEN", "p": [12] },
	{ "s": "REQUERIDOS", "p": [8] },
	{ "s": "RESPALDAR", "p": [8] },
	{ "s": "RESPONDE", "p": [13, 11, 10, 9, 7] },
	{ "s": "RESPONDEN", "p": [16, 14, 8] },
	{ "s": "RESPONSABLE", "p": [5] },
	{ "s": "RESTAURANTE", "p": [2, 16, 15, 14, 13, 1] },
	{ "s": "RESTRINGIDO", "p": [5] },
	{ "s": "RESULTADOS", "p": [8] },
	{ "s": "RESUMA", "p": [11] },
	{ "s": "RESUMEN", "p": [13, 6] },
	{ "s": "RETRASOS", "p": [15] },
	{ "s": "REVERSIBLE", "p": [12] },
	{ "s": "REVIERTE", "p": [13] },
	{ "s": "REVISA", "p": [9, 15, 11, 10, 8, 16, 14, 7] },
	{ "s": "REVISIÓN", "p": [9, 7, 6] },
	{ "s": "RINCÓN", "p": [2, 4, 3] },
	{ "s": "ROJA", "p": [12] },
	{ "s": "ROJO", "p": [13, 6] },
	{ "s": "ROL", "p": [5] },
	{ "s": "ROLES", "p": [5] },
	{ "s": "RÁPIDA", "p": [15] },
	{ "s": "RÁPIDAMENTE", "p": [8] },
	{ "s": "RÁPIDAS", "p": [7] }
]